connected_object_utils/__init__.py
connected_object_utils/object_model_identifier.py
comapsmarthome_connected_object_utils-1.2.0.dist-info/LICENSE
comapsmarthome_connected_object_utils-1.2.0.dist-info/METADATA
comapsmarthome_connected_object_utils-1.2.0.dist-info/WHEEL
comapsmarthome_connected_object_utils-1.2.0.dist-info/top_level.txt
comapsmarthome_connected_object_utils-1.2.0.dist-info/RECORD
