Metadata-Version: 2.1
Name: comapsmarthome-connected-object-utils
Version: 1.2.0
Summary: Connected object helpers for ComapSmartHome
Home-page: 
Author: Aurélien Sylvan
Author-email: aurelien.sylvan@comap.eu
Classifier: Programming Language :: Python :: 3
Classifier: License :: OSI Approved :: MIT License
Classifier: Operating System :: OS Independent
License-File: LICENSE
